action_throttle/__init__.py
action_throttle/admin.py
action_throttle/apps.py
action_throttle/middleware.py
action_throttle/models.py
action_throttle/rest.py
action_throttle/tests.py
action_throttle/throttle.py
action_throttle/throttle_settings.py
action_throttle/urls.py
action_throttle/utils.py
action_throttle/views.py
djangoactionthrottle-0.0.2.dist-info/LICENCE
djangoactionthrottle-0.0.2.dist-info/METADATA
djangoactionthrottle-0.0.2.dist-info/WHEEL
djangoactionthrottle-0.0.2.dist-info/top_level.txt
djangoactionthrottle-0.0.2.dist-info/RECORD
